Metadata-Version: 2.1
Name: mantle2
Version: 0.0.5
Summary: magma standard library (version 2)
Home-page: https://github.com/leonardt/mantle2
Author: Lenny Truong
Author-email: lenny@cs.stanford.edu
License: UNKNOWN
Platform: UNKNOWN
Classifier: Programming Language :: Python :: 3
Classifier: License :: OSI Approved :: BSD License
Classifier: Operating System :: OS Independent
Requires-Python: >=3.8
License-File: LICENSE
